SpatialQC/__init__.py
SpatialQC/__main__.py
SpatialQC/base_qc_plot.py
SpatialQC/basic_statistics.py
SpatialQC/get_input.py
SpatialQC/get_markers.py
SpatialQC/markers_detected_by_filter_cells_genes.py
SpatialQC/markers_detected_by_filter_cells_genes2.py
SpatialQC/markers_detected_by_ngenes_cellbin.py
SpatialQC/slice_score.py
SpatialQC/valid_cells.py
SpatialQC/data/cell_marker.db
SpatialQC/templates/report_template.html
SpatialQC-1.0.3.3.dist-info/METADATA
SpatialQC-1.0.3.3.dist-info/WHEEL
SpatialQC-1.0.3.3.dist-info/entry_points.txt
SpatialQC-1.0.3.3.dist-info/top_level.txt
SpatialQC-1.0.3.3.dist-info/RECORD
