Metadata-Version: 2.1
Name: SpatialQC
Version: 1.0.3.3
Summary: Spatial transcriptome quality control, generate HTML QC report, obtain filtered clean data
Home-page: https://github.com/mgy520/SpatialQC
Author: Mao Guangyao
Requires-Python: >=3.8,<3.9
Requires-Dist: scanpy>=1.9.8
Requires-Dist: joblib>=1.4.2
Requires-Dist: plotly>=5.22.0
Requires-Dist: scrublet>=0.2.3
Requires-Dist: anndata2ri>=1.3.1
